yadoma/__init__.py
yadoma/main.py
yadoma-59.0.post1.dist-info/LICENSE
yadoma-59.0.post1.dist-info/METADATA
yadoma-59.0.post1.dist-info/WHEEL
yadoma-59.0.post1.dist-info/entry_points.txt
yadoma-59.0.post1.dist-info/top_level.txt
yadoma-59.0.post1.dist-info/RECORD
