Metadata-Version: 2.1
Name: yadoma
Version: 59.0.post1
Summary: Yet another dotfile manager
Author: N.V. Haenel & Ingo Fruend
Author-email: github@ingofruend.net
License: APACHE v2.0
Keywords: dotfiles,config management
Classifier: Programming Language :: Python :: 3
License-File: LICENSE
Requires-Dist: docopt
Requires-Dist: pyyaml
